lib/__init__.py
lib/libwebp_linux/__init__.py
lib/libwebp_linux/bin/anim_diff
lib/libwebp_linux/bin/anim_dump
lib/libwebp_linux/bin/cwebp
lib/libwebp_linux/bin/dwebp
lib/libwebp_linux/bin/get_disto
lib/libwebp_linux/bin/gif2webp
lib/libwebp_linux/bin/img2webp
lib/libwebp_linux/bin/vwebp
lib/libwebp_linux/bin/webp_quality
lib/libwebp_linux/bin/webpinfo
lib/libwebp_linux/bin/webpmux
lib/libwebp_linux/doc/cwebp.html
lib/libwebp_linux/doc/cwebp.txt
lib/libwebp_linux/doc/dwebp.html
lib/libwebp_linux/doc/dwebp.txt
lib/libwebp_linux/doc/gif2webp.html
lib/libwebp_linux/doc/gif2webp.txt
lib/libwebp_linux/doc/img2webp.html
lib/libwebp_linux/doc/img2webp.txt
lib/libwebp_linux/doc/vwebp.html
lib/libwebp_linux/doc/vwebp.txt
lib/libwebp_linux/doc/webpinfo.html
lib/libwebp_linux/doc/webpinfo.txt
lib/libwebp_linux/doc/webpmux.html
lib/libwebp_linux/doc/webpmux.txt
lib/libwebp_linux/include/webp/decode.h
lib/libwebp_linux/include/webp/demux.h
lib/libwebp_linux/include/webp/encode.h
lib/libwebp_linux/include/webp/mux.h
lib/libwebp_linux/include/webp/mux_types.h
lib/libwebp_linux/include/webp/types.h
lib/libwebp_linux/lib/__init__.py
lib/libwebp_linux/lib/libwebp.a
lib/libwebp_linux/lib/libwebpdemux.a
lib/libwebp_linux/lib/libwebpmux.a
lib/libwebp_osx/__init__.py
lib/libwebp_osx/bin/anim_diff
lib/libwebp_osx/bin/anim_dump
lib/libwebp_osx/bin/cwebp
lib/libwebp_osx/bin/dwebp
lib/libwebp_osx/bin/get_disto
lib/libwebp_osx/bin/gif2webp
lib/libwebp_osx/bin/img2webp
lib/libwebp_osx/bin/vwebp
lib/libwebp_osx/bin/webp_quality
lib/libwebp_osx/bin/webpinfo
lib/libwebp_osx/bin/webpmux
lib/libwebp_osx/doc/cwebp.html
lib/libwebp_osx/doc/cwebp.txt
lib/libwebp_osx/doc/dwebp.html
lib/libwebp_osx/doc/dwebp.txt
lib/libwebp_osx/doc/gif2webp.html
lib/libwebp_osx/doc/gif2webp.txt
lib/libwebp_osx/doc/img2webp.html
lib/libwebp_osx/doc/img2webp.txt
lib/libwebp_osx/doc/vwebp.html
lib/libwebp_osx/doc/vwebp.txt
lib/libwebp_osx/doc/webpinfo.html
lib/libwebp_osx/doc/webpinfo.txt
lib/libwebp_osx/doc/webpmux.html
webptools-0.0.2.dist-info/LICENSE
webptools-0.0.2.dist-info/METADATA
webptools-0.0.2.dist-info/WHEEL
webptools-0.0.2.dist-info/top_level.txt
webptools-0.0.2.dist-info/RECORD
