Metadata-Version: 2.1
Name: webptools
Version: 0.0.2
Summary: webptools is a Webp image conversion package for python
Home-page: https://github.com/scionoftech/webptools
Author: Sai Kumar Yava
Author-email: saikumar.geek@gmail.com
License: MIT
Keywords: webp,converter,image
Platform: UNKNOWN
Classifier: Development Status :: 5 - Production/Stable
Classifier: Programming Language :: Python
Classifier: Programming Language :: Python :: 3
Classifier: Programming Language :: Python :: 3.5
Classifier: Programming Language :: Python :: 3.6
Classifier: Programming Language :: Python :: 3.7
Classifier: Programming Language :: Python :: Implementation :: CPython
Classifier: Programming Language :: Python :: Implementation :: PyPy
Classifier: License :: OSI Approved :: MIT License
